searxng_mcp_server/__init__.py
searxng_mcp_server/config.py
searxng_mcp_server/log.py
searxng_mcp_server/main.py
searxng_mcp_server/models.py
searxng_mcp_server/tools.py
searxng_mcp_server-0.1.7.dist-info/METADATA
searxng_mcp_server-0.1.7.dist-info/WHEEL
searxng_mcp_server-0.1.7.dist-info/entry_points.txt
searxng_mcp_server-0.1.7.dist-info/RECORD
