Metadata-Version: 2.4
Name: searxng-mcp-server
Version: 0.1.7
Summary: MCP Server for SearxNG
Project-URL: Homepage, https://github.com/IceWreck/SearxNG-MCP-Server
Project-URL: Repository, https://github.com/IceWreck/SearxNG-MCP-Server
Author-email: Anchit Bajaj <ab@abifog.com>
Requires-Python: >=3.11
Requires-Dist: fastmcp>=2.12.4
Requires-Dist: httpx>=0.28.1
Requires-Dist: markitdown[pdf]>=0.1.3
Requires-Dist: pydantic>=2.11.10
